{
  "schema_version": "1.0",
  "source": "github",
  "last_updated": "2026-06-29T20:47:21Z",
  "last_update_source": "photo",
  "totals": {
    "stickers_total": 980,
    "owned_total": 956,
    "missing_total": 24,
    "progress_percent": 97.55
  },
  "last_update_result": {
    "operation": "add",
    "requested": [
      "CRO06",
      "MAR12",
      "MEX19",
      "USA09"
    ],
    "added": [
      "CRO06",
      "MAR12",
      "MEX19",
      "USA09"
    ],
    "removed": [],
    "already_owned": [],
    "already_missing": [],
    "not_found": [],
    "invalid": []
  }
}
